pwdf/__init__.py
pwdf/pwdf.py
pwdf-1.0.1.dist-info/METADATA
pwdf-1.0.1.dist-info/WHEEL
pwdf-1.0.1.dist-info/entry_points.txt
pwdf-1.0.1.dist-info/top_level.txt
pwdf-1.0.1.dist-info/RECORD
